[
  {
    "id": "LIE-01",
    "name": "リヒテンシュタイン全域",
    "name_en": "Entire Liechtenstein",
    "reason": "リヒテンシュタインは国土が狭小であり、地理的・経済的・文化的な特徴が国全体に均質に分布しているため、単一のエリアとして定義するのが最も適切である。ライン川流域の谷間とアルプス山脈の山岳地帯という地形的な特徴は存在するが、国全体が一体として機能している。",
    "geometry_wkt": "POLYGON ((9.463348 47.271600, 9.639816 47.271600, 9.639816 47.034567, 9.463348 47.034567, 9.463348 47.271600))",
    "area_id": 366,
    "source_row_index": 366,
    "iso_a3_source": "LIE",
    "iso_a3": "LIE",
    "area_seq_in_source": 1
  }
]