[
  {
    "id": "PRK-01",
    "name": "北西平野・平壌圏",
    "name_en": "Northwestern Plains and Pyongyang Region",
    "reason": "西部の河谷平野と平壌を含む人口・農業・交通の中核地域であり、北朝鮮で最も低地性が強い地域であるため。",
    "geometry_wkt": "POLYGON ((123.442383 40.245992, 126.628418 40.245992, 126.628418 37.535866, 123.442383 37.535866, 123.442383 40.245992))",
    "area_id": 499,
    "source_row_index": 499,
    "iso_a3_source": "PRK",
    "iso_a3": "PRK",
    "area_seq_in_source": 1
  },
  {
    "id": "PRK-02",
    "name": "北部内陸高地",
    "name_en": "Northern Interior Highlands",
    "reason": "中朝国境寄りの内陸高地であり、山地・高原が卓越し、人口希薄な北部内陸の性格をまとめて表現しやすいため。",
    "geometry_wkt": "POLYGON ((124.123535 41.902277, 127.584229 41.902277, 127.584229 40.245992, 124.123535 40.245992, 124.123535 41.902277))",
    "area_id": 500,
    "source_row_index": 500,
    "iso_a3_source": "PRK",
    "iso_a3": "PRK",
    "area_seq_in_source": 2
  },
  {
    "id": "PRK-03",
    "name": "北東山地・東岸地域",
    "name_en": "Northeastern Highlands and East Coast",
    "reason": "Hamgyŏng Mountains と Kaema Highlands に連なる北東山地と東岸北部を含み、北朝鮮でも最も山地性の強い地域であるため。",
    "geometry_wkt": "POLYGON ((127.584229 43.076913, 131.022949 43.076913, 131.022949 40.262761, 127.584229 40.262761, 127.584229 43.076913))",
    "area_id": 501,
    "source_row_index": 501,
    "iso_a3_source": "PRK",
    "iso_a3": "PRK",
    "area_seq_in_source": 3
  },
  {
    "id": "PRK-04",
    "name": "南東部・江原地域",
    "name_en": "Southeastern Region and Kangwon Area",
    "reason": "東海岸南部と中南部山地を含む地域であり、東側の海岸帯と南寄りの山地・境界地帯を一体で扱いやすいため。",
    "geometry_wkt": "POLYGON ((126.617432 40.254377, 129.199219 40.254377, 129.199219 37.692514, 126.617432 37.692514, 126.617432 40.254377))",
    "area_id": 502,
    "source_row_index": 502,
    "iso_a3_source": "PRK",
    "iso_a3": "PRK",
    "area_seq_in_source": 4
  }
]