{
  "iso_a3": "GMB",
  "area_count": 1,
  "country_bbox": {
    "minx": -17.166667,
    "maxx": -13.436279,
    "miny": 13.0,
    "maxy": 13.891411
  },
  "areas": [
    {
      "id": "GMB-01",
      "area_id": 250,
      "area_seq_in_source": 1,
      "name": "ガンビア全土",
      "name_en": "The Gambia",
      "reason": "ガンビアはアフリカ大陸で最も小さい国であり、地理的にも地理的にも分割するほど大きくないため、単一のエリアとして定義することが最も適切である。",
      "geometry_wkt": "POLYGON ((-17.166667 13.891411, -13.436279 13.891411, -13.436279 13.000000, -17.166667 13.000000, -17.166667 13.891411))",
      "bbox": {
        "minx": -17.166667,
        "maxx": -13.436279,
        "miny": 13.0,
        "maxy": 13.891411
      },
      "centroid": {
        "x": -15.301473,
        "y": 13.445705
      },
      "size": {
        "width": 3.730388,
        "height": 0.891411
      },
      "relative_position": {
        "x_norm": 0.5,
        "y_norm": 0.5,
        "zone": [
          "center"
        ]
      },
      "relations": {
        "west_of": [],
        "east_of": [],
        "north_of": [],
        "south_of": [],
        "overlaps": []
      },
      "map32_summary": {
        "cell_count": 706,
        "dominant_landcover": "OCEAN",
        "dominant_t2": "TROPICAL",
        "dominant_e2": "LOW",
        "dominant_p2": "LOW",
        "landcover_ratio": {
          "OCEAN": 0.289,
          "SHRUB": 0.2776,
          "CROPLAND": 0.2266,
          "TREE": 0.0666,
          "MANGROVE": 0.0567,
          "WETLAND": 0.0354,
          "WATER": 0.0269,
          "GRASS": 0.0127,
          "BUILT": 0.0085
        },
        "temperature_ratio": {
          "TROPICAL": 1.0
        },
        "elevation_ratio": {
          "LOW": 1.0
        },
        "precip_ratio": {
          "LOW": 0.6941,
          "MID": 0.3059
        },
        "flags_ratio": {
          "water": 0.8555,
          "forest": 0.4079,
          "cropland": 0.2266,
          "built": 0.0085
        },
        "cell_bbox_xy": {
          "min_x": 3906,
          "max_x": 3987,
          "min_y": 1828,
          "max_y": 1848
        },
        "cell_centroid": {
          "x": 3940.18,
          "y": 1837.47,
          "lon": -15.805005,
          "lat": 13.417906
        }
      }
    }
  ]
}